tests/__init__.py
tests/context.py
tests/mocked_ops.py
tests/test_prep_run_vasp.py
tests/test_prep_vasp.py
tests/test_run_vasp.py
tests/test_vasp_inputs.py
fpoptest-0.0.1.dist-info/LICENSE
fpoptest-0.0.1.dist-info/METADATA
fpoptest-0.0.1.dist-info/WHEEL
fpoptest-0.0.1.dist-info/top_level.txt
fpoptest-0.0.1.dist-info/RECORD
