Metadata-Version: 2.1
Name: fpoptest
Version: 0.0.1
Summary: operators about first principle caculations
Home-page: https://github.com/Chengqian-Zhang/FP_OPs
Author: Chengqian Zhang
Author-email: 2043899742@qq.com
Classifier: Programming Language :: Python :: 3
Classifier: License :: OSI Approved :: GNU Lesser General Public License v3 (LGPLv3)
Classifier: Operating System :: OS Independent
Provides: fpoptest
Requires-Python: >=3.8
License-File: LICENSE
Requires-Dist: pydflow (>=1.6.27)
Requires-Dist: lbg (>=1.2.13)
Requires-Dist: dpdata (>=0.2.13)
Requires-Dist: matplotlib
Requires-Dist: phonopy
Requires-Dist: seekpath
